{
    "3": {
        "0": [
            "자판기는 제대로 작동하고 있다.",
            "\\!음료수를 뽑기에는 돈이 없다."
        ]
    },
    "4": {
        "0": [
            "공중전화 부스.",
            "\\!미약하게나마 불이 켜져 있다."
        ]
    },
    "6": {
        "0": [
            " ",
            " ",
            " ",
            "본격적으로 일을 시작하기 전에",
            "마지막으로 정리해 볼까.",
            "학교가 강한 원혼에 의해 공간이 뒤틀렸고,",
            "거기에 그 학생들이 갇혀버렸어.",
            "계획이 조금 틀어져 버렸으니.",
            "\\!우선 그 학생들부터 구해줘야겠지.",
            "...표정을 보니 마음에 들지 않는 눈치구만.",
            "\\!심정은 이해하지만, 최대한 이성적으로 생각하자고.",
            "시간은 오늘 새벽 5시. 동이 트기 전 까지다.",
            "\\!아침이 밝아오기 전에 모두 마무리 지어야 해.",
            "그럼, 난 먼저 들어가도록 하지."
        ]
    },
    "10": {
        "1": [
            "아직은 때가 아니야."
        ]
    },
    "11": {
        "0": [
            "초대 교장의 모습이 새겨진 동상이다.",
            "초대 교장의 모습이 새겨진 동상이다.",
            "\\!옆에서 봐도 특별한 건 없다."
        ]
    },
    "12": {
        "0": [
            "낡은 계수대다.",
            "물이 나오지 않는다."
        ]
    },
    "13": {
        "0": [
            "낡은 계수대다.",
            "물이 나오지 않는다."
        ]
    },
    "14": {
        "0": [
            "낡은 계수대다.",
            "물이 나오지 않는다."
        ]
    },
    "15": {
        "0": [
            "낡은 계수대다.",
            "물이 나오지 않는다."
        ]
    },
    "16": {
        "0": [
            "낡은 계수대다.",
            "물이 나오지 않는다."
        ]
    },
    "17": {
        "0": [
            "낡은 계수대다.",
            "물이 나오지 않는다."
        ]
    },
    "18": {
        "0": [
            "창문 안은 매우 어두워서 보이지 않는다."
        ]
    },
    "19": {
        "0": [
            "녹슨 실외기.",
            "\\!작동하지 않는 것 같다."
        ]
    },
    "20": {
        "0": [
            "화단에 이름모를 꽃들이 피어 있다."
        ]
    },
    "21": {
        "0": [
            "화단에 이름모를 꽃들이 피어 있다."
        ]
    },
    "22": {
        "0": [
            "화단에 이름모를 꽃들이 피어 있다."
        ]
    },
    "23": {
        "0": [
            "화단에 이름모를 꽃들이 피어 있다."
        ]
    },
    "24": {
        "0": [
            "화단에 이름모를 꽃들이 피어 있다."
        ]
    },
    "25": {
        "0": [
            "화단에 이름모를 꽃들이 피어 있다."
        ]
    },
    "27": {
        "0": [
            "악취가 피어오르는 쓰레기통"
        ]
    },
    "28": {
        "0": [
            "글씨가 써져 있다.",
            "- 수도꼭지에 입을 대지 마시오",
            "- 물을 아낍시다"
        ]
    },
    "29": {
        "0": [
            "작은 묘목이 심어져 있다."
        ]
    },
    "30": {
        "0": [
            "작은 묘목이 심어져 있다."
        ]
    },
    "31": {
        "0": [
            "작은 묘목이 심어져 있다."
        ]
    },
    "32": {
        "0": [
            "작은 묘목이 심어져 있다."
        ]
    },
    "33": {
        "0": [
            "작은 묘목이 심어져 있다."
        ]
    },
    "34": {
        "0": [
            "작은 묘목이 심어져 있다."
        ]
    },
    "35": {
        "0": [
            "작은 묘목이 심어져 있다."
        ]
    },
    "36": {
        "0": [
            "작은 묘목이 심어져 있다."
        ]
    },
    "37": {
        "0": [
            "작은 묘목이 심어져 있다."
        ]
    },
    "38": {
        "0": [
            "작은 묘목이 심어져 있다."
        ]
    },
    "39": {
        "0": [
            "작은 묘목이 심어져 있다."
        ]
    },
    "40": {
        "0": [
            "작은 묘목이 심어져 있다."
        ]
    },
    "41": {
        "0": [
            "작은 묘목이 심어져 있다."
        ]
    },
    "42": {
        "0": [
            "작은 묘목이 심어져 있다."
        ]
    },
    "43": {
        "0": [
            "작은 묘목이 심어져 있다."
        ]
    },
    "44": {
        "0": [
            "작은 묘목이 심어져 있다."
        ]
    },
    "45": {
        "0": [
            "작은 묘목이 심어져 있다."
        ]
    },
    "46": {
        "0": [
            "작은 묘목이 심어져 있다."
        ]
    },
    "47": {
        "0": [
            "자전거 거치대가 세워져 있다."
        ]
    },
    "48": {
        "0": [
            "자전거 거치대가 세워져 있다."
        ]
    },
    "49": {
        "0": [
            "자전거 거치대가 세워져 있다."
        ]
    },
    "50": {
        "0": [
            "자전거 거치대가 세워져 있다."
        ]
    },
    "51": {
        "0": [
            "자전거 거치대가 세워져 있다."
        ]
    },
    "52": {
        "0": [
            "자전거 거치대가 세워져 있다."
        ]
    },
    "53": {
        "0": [
            "신호등은 붉은 빛을 내며 점등하고 있다."
        ]
    },
    "54": {
        "0": [
            "준비는 다 됐나?",
            [
                "그래",
                "아직"
            ],
            "좋아. 그럼 들어가 볼까.",
            "그래? \\!시간이 많지 않으니까 서둘러."
        ]
    }
}